peacepie/__init__.py
peacepie/adaptor.py
peacepie/log_conf.py
peacepie/loglistener.py
peacepie/msg_factory.py
peacepie/multimanager.py
peacepie/params.py
peacepie/peace_system.py
peacepie/assist/auxiliaries.py
peacepie/assist/dir_opers.py
peacepie/assist/json_util.py
peacepie/assist/log_util.py
peacepie/assist/misc.py
peacepie/assist/rsa_util.py
peacepie/assist/serialization.py
peacepie/assist/terminal_util.py
peacepie/assist/thread_util.py
peacepie/assist/timer.py
peacepie/assist/version.py
peacepie/control/admin.py
peacepie/control/delivery.py
peacepie/control/head_prime_admin.py
peacepie/control/internal_starter.py
peacepie/control/package_loader.py
peacepie/control/prime_admin.py
peacepie/control/process_admin.py
peacepie/control/safe_admin.py
peacepie/control/series_admin.py
peacepie/control/ticker_admin.py
peacepie/control/actors/actor_admin.py
peacepie/control/actors/actor_agent.py
peacepie/control/actors/actor_loader.py
peacepie/control/actors/actor_recreator.py
peacepie/control/actors/actor_seeker.py
peacepie/control/actors/package_admin.py
peacepie/control/inter/inter_queue.py
peacepie/control/inter/inter_server.py
peacepie/control/intra/intra_link.py
peacepie/control/intra/intra_queue.py
peacepie/resources/config/app_starter_example.py
peacepie/resources/config/log.cfg
peacepie/resources/config/peacepie.cfg
peacepie/resources/config/safe.cfg
peacepie-0.2.2.dist-info/licenses/LICENSE
peacepie-0.2.2.dist-info/METADATA
peacepie-0.2.2.dist-info/WHEEL
peacepie-0.2.2.dist-info/top_level.txt
peacepie-0.2.2.dist-info/RECORD
