Metadata-Version: 2.4
Name: peacepie
Version: 0.2.2
Summary: Простая система акторов
Author-email: Владимир Молодцов <vmol@mail.ru>
License-File: LICENSE
Dynamic: license-file
